findlibs/__init__.py
findlibs-0.1.0.dist-info/LICENSE
findlibs-0.1.0.dist-info/METADATA
findlibs-0.1.0.dist-info/WHEEL
findlibs-0.1.0.dist-info/top_level.txt
findlibs-0.1.0.dist-info/zip-safe
findlibs-0.1.0.dist-info/RECORD
